atriumdb/__init__.py
atriumdb/adb_functions.py
atriumdb/adb_remote.py
atriumdb/atrium_sdk.py
atriumdb/binary_signal_converter.py
atriumdb/block.py
atriumdb/block_wrapper.py
atriumdb/file_api.py
atriumdb/interval_overlap.py
atriumdb/mem_cache.py
atriumdb/write_buffer.py
atriumdb/cli/__init__.py
atriumdb/cli/atriumdb_cli.py
atriumdb/cli/hello.py
atriumdb/cli/sdk.py
atriumdb/helpers/__init__.py
atriumdb/helpers/block_calculations.py
atriumdb/helpers/block_constants.py
atriumdb/helpers/config.toml
atriumdb/helpers/mariadb_env_cred.py
atriumdb/helpers/settings.py
atriumdb/helpers/sql_helpers.py
atriumdb/helpers/sql_tables.py
atriumdb/helpers/sql_wait_wrapper.py
atriumdb/helpers/type_helpers.py
atriumdb/intervals/__init__.py
atriumdb/intervals/compact.py
atriumdb/intervals/difference.py
atriumdb/intervals/intersection.py
atriumdb/intervals/intervals.py
atriumdb/intervals/union.py
atriumdb/sql_handler/__init__.py
atriumdb/sql_handler/sql_constants.py
atriumdb/sql_handler/sql_handler.py
atriumdb/sql_handler/sql_helper.py
atriumdb/sql_handler/maria/__init__.py
atriumdb/sql_handler/maria/maria_functions.py
atriumdb/sql_handler/maria/maria_handler.py
atriumdb/sql_handler/maria/maria_tables.py
atriumdb/sql_handler/sqlite/__init__.py
atriumdb/sql_handler/sqlite/sqlite_functions.py
atriumdb/sql_handler/sqlite/sqlite_handler.py
atriumdb/sql_handler/sqlite/sqlite_tables.py
atriumdb/transfer/__init__.py
atriumdb/transfer/adb/__init__.py
atriumdb/transfer/adb/csv.py
atriumdb/transfer/adb/dataset.py
atriumdb/transfer/adb/datestring_conversion.py
atriumdb/transfer/adb/definition.py
atriumdb/transfer/adb/devices.py
atriumdb/transfer/adb/labels.py
atriumdb/transfer/adb/measures.py
atriumdb/transfer/adb/numpy.py
atriumdb/transfer/adb/parquet.py
atriumdb/transfer/adb/patients.py
atriumdb/transfer/adb/tsc.py
atriumdb/transfer/adb/wfdb.py
atriumdb/transfer/cohort/__init__.py
atriumdb/transfer/cohort/cohort_yaml.py
atriumdb/transfer/formats/__init__.py
atriumdb/transfer/formats/dataset.py
atriumdb-2.5.1.dist-info/licenses/LICENSE
atriumdb-2.5.1.dist-info/METADATA
atriumdb-2.5.1.dist-info/WHEEL
atriumdb-2.5.1.dist-info/entry_points.txt
atriumdb-2.5.1.dist-info/top_level.txt
atriumdb-2.5.1.dist-info/RECORD
