Metadata-Version: 2.4
Name: atriumdb
Version: 2.5.1
Summary: Timeseries Database
Author: Robert Greer, William Dixon, Spencer Vecile
Author-email: Robert Greer <robert.greer@sickkids.ca>, William Dixon <will.dixon@sickkids.ca>, Spencer Vecile <spencer.vecile@sickkids.ca>
Maintainer-email: "William Dixon, Spencer Vecile" <laussen.labs@sickkids.ca>, William Dixon <will.dixon@sickkids.ca>, Spencer Vecile <spencer.vecile@sickkids.ca>
License: 
Project-URL: Homepage, https://atriumdb.io
Project-URL: Documentation, https://docs.atriumdb.io/
Keywords: atriumdb,timeseries,database,waveform,medical data,machine learning,data,data science
Classifier: Programming Language :: Python :: 3
Classifier: Programming Language :: Python :: 3.10
Classifier: Programming Language :: Python :: 3.11
Classifier: Programming Language :: Python :: 3.12
Classifier: License :: OSI Approved :: GNU General Public License v3 (GPLv3)
Classifier: Operating System :: POSIX :: Linux
Classifier: Operating System :: Microsoft :: Windows
Classifier: Intended Audience :: Healthcare Industry
Classifier: Intended Audience :: Science/Research
Classifier: Topic :: Database
Classifier: Topic :: Scientific/Engineering :: Bio-Informatics
Classifier: Topic :: Scientific/Engineering :: Artificial Intelligence
Classifier: Topic :: Scientific/Engineering :: Medical Science Apps.
Classifier: Development Status :: 5 - Production/Stable
License-File: LICENSE
Requires-Dist: tomli; python_version < "3.11"
Requires-Dist: numpy<3,>=2.2.6
Requires-Dist: PyYAML>=6.0.2
Requires-Dist: tqdm<5,>=4.67.1
Provides-Extra: mariadb
Requires-Dist: mariadb==1.1.13; extra == "mariadb"
Provides-Extra: remote
Requires-Dist: requests<3,>=2.32.4; extra == "remote"
Requires-Dist: PyJWT[crypto]<3,>=2.6.0; extra == "remote"
Requires-Dist: python-dotenv<1,>=0.21.1; extra == "remote"
Requires-Dist: websockets<16,>=15.0.1; extra == "remote"
Provides-Extra: cli
Requires-Dist: requests<3,>=2.32.4; extra == "cli"
Requires-Dist: qrcodeT<2,>=1.0.4; extra == "cli"
Requires-Dist: click<9,>=8.2.1; extra == "cli"
Requires-Dist: pandas<3,>=2.3.1; extra == "cli"
Requires-Dist: tabulate<1,>=0.9.0; extra == "cli"
Requires-Dist: fastparquet==2024.11.0; extra == "cli"
Requires-Dist: python-dotenv<1,>=0.21.1; extra == "cli"
Requires-Dist: PyYAML>=6.0.2; extra == "cli"
Provides-Extra: all
Requires-Dist: mariadb==1.1.13; extra == "all"
Requires-Dist: requests<3,>=2.32.4; extra == "all"
Requires-Dist: PyJWT[crypto]<3,>=2.6.0; extra == "all"
Requires-Dist: websockets<16,>=15.0.1; extra == "all"
Requires-Dist: qrcodeT<2,>=1.0.4; extra == "all"
Requires-Dist: python-dotenv<1,>=0.21.1; extra == "all"
Requires-Dist: click<9,>=8.2.1; extra == "all"
Requires-Dist: pandas<3,>=2.3.1; extra == "all"
Requires-Dist: tabulate<1,>=0.9.0; extra == "all"
Requires-Dist: fastparquet<2025,>=2024.11.0; extra == "all"
Requires-Dist: wfdb<5,>=4.2.0; extra == "all"
Requires-Dist: pyarrow<22,>=21.0.0; extra == "all"
Requires-Dist: tzdata<2026,>=2025.2; extra == "all"
Provides-Extra: testing
Requires-Dist: mariadb==1.1.13; extra == "testing"
Requires-Dist: requests<3,>=2.32.4; extra == "testing"
Requires-Dist: PyJWT[crypto]<3,>=2.6.0; extra == "testing"
Requires-Dist: websockets<16,>=15.0.1; extra == "testing"
Requires-Dist: qrcodeT<2,>=1.0.4; extra == "testing"
Requires-Dist: python-dotenv<1,>=0.21.1; extra == "testing"
Requires-Dist: click<9,>=8.2.1; extra == "testing"
Requires-Dist: pandas<3,>=2.3.1; extra == "testing"
Requires-Dist: tabulate<1,>=0.9.0; extra == "testing"
Requires-Dist: fastparquet<2025,>=2024.11.0; extra == "testing"
Requires-Dist: wfdb<5,>=4.2.0; extra == "testing"
Requires-Dist: pyarrow<22,>=21.0.0; extra == "testing"
Requires-Dist: tzdata<2026,>=2025.2; extra == "testing"
Requires-Dist: names<1,>=0.3.0; extra == "testing"
Requires-Dist: uvicorn<1,>=0.35.0; extra == "testing"
Requires-Dist: pytest>=7.2.1; extra == "testing"
Requires-Dist: fastapi<1,>=0.95.0; extra == "testing"
Dynamic: license-file
